{
  "photos": [
    {
      "id": 1,
      "url": "https://via.placeholder.com/600/1fe46f",
      "likes": 61,
      "comments": [
        "culpa eu duis"
      ],
      "description": "Proin risus."
    },
    {
      "id": 2,
      "url": "https://via.placeholder.com/600/56acb2",
      "likes": 8,
      "comments": [
        "labore Lorem dolor",
        "deserunt exercitation dolor"
      ],
      "description": "Proin interdum mauris non ligula pellentesque ultrices."
    },
    {
      "id": 3,
      "url": "https://via.placeholder.com/600/8985dc",
      "likes": 49,
      "comments": [
        "aute nisi dolor",
        "irure in ipsum",
        "pariatur dolor culpa",
        "consectetur magna sit",
        "Lorem non sunt"
      ],
      "description": "Suspendisse potenti."
    },
    {
      "id": 4,
      "url": "https://via.placeholder.com/600/5e12c6",
      "likes": 86,
      "comments": [
        "enim est minim",
        "sunt duis qui",
        "veniam reprehenderit cillum",
        "eiusmod laborum esse",
        "Lorem aliquip ipsum"
      ],
      "description": "Nulla facilisi."
    },
    {
      "id": 5,
      "url": "https://via.placeholder.com/600/45601a",
      "likes": 73,
      "comments": [
        "tempor officia commodo"
      ],
      "description": "Sed ante."
    },
    {
      "id": 6,
      "url": "https://via.placeholder.com/600/e924e6",
      "likes": 57,
      "comments": [
        "aliquip velit consectetur",
        "deserunt ut tempor"
      ],
      "description": "Phasellus id sapien in sapien iaculis congue."
    },
    {
      "id": 7,
      "url": "https://via.placeholder.com/600/8f209a",
      "likes": 70,
      "comments": [
        "qui deserunt commodo",
        "dolor aliquip labore"
      ],
      "description": "Integer a nibh."
    },
    {
      "id": 8,
      "url": "https://via.placeholder.com/600/5e3a73",
      "likes": 62,
      "comments": [
        "ad ullamco consequat",
        "nostrud ad occaecat",
        "laboris culpa voluptate",
        "sunt mollit proident",
        "minim est deserunt"
      ],
      "description": "Aenean fermentum."
    },
    {
      "id": 9,
      "url": "https://via.placeholder.com/600/474645",
      "likes": 33,
      "comments": [
        "deserunt nostrud non",
        "reprehenderit occaecat nostrud",
        "voluptate ex consectetur",
        "in qui tempor",
        "minim excepteur occaecat"
      ],
      "description": "Donec posuere metus vitae ipsum."
    },
    {
      "id": 10,
      "url": "https://via.placeholder.com/600/c984bf",
      "likes": 47,
      "comments": [
        "ea mollit laboris",
        "veniam qui duis",
        "reprehenderit sint dolor"
      ],
      "description": "Integer non velit."
    },
    {
      "id": 11,
      "url": "https://via.placeholder.com/600/392537",
      "likes": 25,
      "comments": [
        "occaecat eu quis",
        "ipsum nulla exercitation",
        "et Lorem id"
      ],
      "description": "Nam ultrices, libero non mattis pulvinar, nulla pede ullamcorper augue, a suscipit nulla elit ac nulla."
    },
    {
      "id": 12,
      "url": "https://via.placeholder.com/600/602b9e",
      "likes": 42,
      "comments": [
        "aliqua ex est",
        "esse excepteur minim"
      ],
      "description": "Pellentesque viverra pede ac diam."
    },
    {
      "id": 13,
      "url": "https://via.placeholder.com/600/372c93",
      "likes": 33,
      "comments": [
        "ad cillum et"
      ],
      "description": "Donec posuere metus vitae ipsum."
    },
    {
      "id": 14,
      "url": "https://via.placeholder.com/600/a7c272",
      "likes": 8,
      "comments": [
        "aute tempor amet",
        "culpa tempor voluptate",
        "nisi ullamco fugiat",
        "et aliqua ea",
        "proident ut ullamco"
      ],
      "description": "Nam congue, risus semper porta volutpat, quam pede lobortis ligula, sit amet eleifend pede libero quis orci."
    },
    {
      "id": 15,
      "url": "https://via.placeholder.com/600/c70a4d",
      "likes": 96,
      "comments": [
        "irure nostrud nostrud",
        "commodo exercitation eiusmod"
      ],
      "description": "Donec ut mauris eget massa tempor convallis."
    },
    {
      "id": 16,
      "url": "https://via.placeholder.com/600/35185e",
      "likes": 65,
      "comments": [
        "nulla et quis",
        "fugiat ipsum exercitation",
        "elit ad nostrud"
      ],
      "description": "Vivamus vel nulla eget eros elementum pellentesque."
    },
    {
      "id": 17,
      "url": "https://via.placeholder.com/600/c96cad",
      "likes": 42,
      "comments": [
        "esse commodo sint",
        "laborum eu nulla"
      ],
      "description": "Cum sociis natoque penatibus et magnis dis parturient montes, nascetur ridiculus mus."
    },
    {
      "id": 18,
      "url": "https://via.placeholder.com/600/4d564d",
      "likes": 28,
      "comments": [
        "magna quis deserunt",
        "aliquip pariatur do",
        "mollit incididunt sit",
        "dolor esse culpa"
      ],
      "description": "Morbi porttitor lorem id ligula."
    },
    {
      "id": 19,
      "url": "http://dummyimage.com/238x143.jpg/dddddd/000000",
      "likes": 82,
      "comments": [
        "nostrud sit voluptate",
        "qui do amet",
        "anim ut ipsum",
        "reprehenderit irure sint",
        "esse enim eiusmod",
        "laborum adipisicing reprehenderit",
        "amet dolore tempor"
      ],
      "description": "Vestibulum ante ipsum primis in faucibus orci luctus et ultrices posuere cubilia Curae; Donec pharetra, magna vestibulum aliquet ultrices, erat tortor sollicitudin mi, sit amet lobortis sapien sapien non mi."
    },
    {
      "id": 20,
      "url": "http://dummyimage.com/160x133.jpg/ff4444/ffffff",
      "likes": 17,
      "comments": [
        "esse et sunt"
      ],
      "description": "Suspendisse accumsan tortor quis turpis."
    },
    {
      "id": 21,
      "url": "https://via.placeholder.com/600/ea51da",
      "likes": 61,
      "comments": [
        "Lorem excepteur non",
        "anim officia voluptate",
        "et magna tempor",
        "in excepteur occaecat"
      ],
      "description": "Nulla ac enim."
    },
    {
      "id": 22,
      "url": "https://via.placeholder.com/600/4f5b8d",
      "likes": 49,
      "comments": [
        "cupidatat ea tempor"
      ],
      "description": "Mauris sit amet eros."
    },
    {
      "id": 23,
      "url": "https://via.placeholder.com/600/1e71a2",
      "likes": 70,
      "comments": [
        "aliquip aute fugiat",
        "cillum proident est",
        "fugiat ad sint",
        "sint est in",
        "et consequat voluptate"
      ],
      "description": "Aenean lectus."
    },
    {
      "id": 24,
      "url": "https://via.placeholder.com/600/3a0b95",
      "likes": 64,
      "comments": [
        "enim exercitation mollit",
        "esse consequat nulla"
      ],
      "description": "Nullam sit amet turpis elementum ligula vehicula consequat."
    },
    {
      "id": 25,
      "url": "https://via.placeholder.com/600/659403",
      "likes": 38,
      "comments": [
        "occaecat Lorem eu",
        "quis pariatur laboris"
      ],
      "description": "Vivamus in felis eu sapien cursus vestibulum."
    },
    {
      "id": 26,
      "url": "https://via.placeholder.com/600/659424",
      "likes": 68,
      "comments": [
        "quis pariatur laboris"
      ],
      "description": "Vivtibulum."
    }
  ]
}